{"name":"searchTest","id":"tests.AccPageTests:searchTest","testCaseName":"tests.AccPageTests","testSteps":[{"number":1,"description":"Is on login page","duration":3171,"startTime":"2022-02-15T16:18:12.440429100+05:30[Asia/Calcutta]","screenshots":[{"screenshot":"ec27f8230c9a296ad5348454ef05edf39e2ff57c7f893f92397914377ac1e2a0.png","timeStamp":1644922092781},{"screenshot":"ec27f8230c9a296ad5348454ef05edf39e2ff57c7f893f92397914377ac1e2a0.png","timeStamp":1644922095611}],"result":"SUCCESS","precondition":false,"level":0},{"number":2,"description":"Search product: summer, Summer Dresses","duration":8214,"startTime":"2022-02-15T16:18:15.613859100+05:30[Asia/Calcutta]","screenshots":[{"screenshot":"0a1d710d7ae9211f52b2bc8ebf18efe525186b1f297c3da4805059c0d7c70efe.png","timeStamp":1644922103828}],"result":"SUCCESS","precondition":false,"level":0}],"userStory":{"id":"tests.AccPageTests","storyName":"Acc page tests","displayName":"Acc page tests","storyClassName":"tests.AccPageTests","path":"tests","type":"story"},"featureTag":{"name":"Tests/Acc page tests","type":"story","displayName":"Tests/Acc page tests"},"title":"Search test","tags":[{"name":"Tests/Acc page tests","type":"story","displayName":"Tests/Acc page tests"}],"startTime":"2022-02-15T16:18:12.425431900+05:30[Asia/Calcutta]","duration":11404,"projectKey":"","sessionId":"7fd98db549d06cff4de92bf19915e8c9","driver":"chrome","isManualTestingUpToDate":false,"manual":false,"testSource":"JUnit","order":0,"result":"SUCCESS"}